README.md
pytest_jasmine.py
setup.py
pytest_jasmine.egg-info/PKG-INFO
pytest_jasmine.egg-info/SOURCES.txt
pytest_jasmine.egg-info/dependency_links.txt
pytest_jasmine.egg-info/entry_points.txt
pytest_jasmine.egg-info/requires.txt
pytest_jasmine.egg-info/top_level.txt